cctrusted_base/__init__.py
cctrusted_base/api.py
cctrusted_base/binaryblob.py
cctrusted_base/ccel.py
cctrusted_base/ccreport.py
cctrusted_base/eventlog.py
cctrusted_base/imr.py
cctrusted_base/tcg.py
cctrusted_base/tcgcel.py
cctrusted_base/tdx/__init__.py
cctrusted_base/tdx/common.py
cctrusted_base/tdx/quote.py
cctrusted_base/tdx/report.py
cctrusted_base/tdx/rtmr.py
cctrusted_base/tpm/pcr.py
cctrusted_base/tpm/quote.py
cctrusted_base-0.5.0.dist-info/METADATA
cctrusted_base-0.5.0.dist-info/WHEEL
cctrusted_base-0.5.0.dist-info/top_level.txt
cctrusted_base-0.5.0.dist-info/RECORD
